ramorm/__init__.py
ramorm/fields.py
ramorm/model.py
ramorm/orm.py
ramorm/primitives.py
ramorm-0.0.11.dist-info/LICENSE
ramorm-0.0.11.dist-info/METADATA
ramorm-0.0.11.dist-info/WHEEL
ramorm-0.0.11.dist-info/top_level.txt
ramorm-0.0.11.dist-info/RECORD
