Metadata-Version: 2.1
Name: ramorm
Version: 0.0.11
Summary: Model based ORM in RAM
Home-page: https://github.com/Yurzs/ramorm
Author: Yurzs
License: UNKNOWN
Platform: UNKNOWN
Classifier: Programming Language :: Python :: 3
Classifier: License :: OSI Approved :: MIT License
Classifier: Operating System :: OS Independent
Classifier: Development Status :: 3 - Alpha
